LICENSE
README.md
setup.py
FlightHopper/__init__.py
FlightHopper/airport_city_info.py
FlightHopper/main.py
FlightHopper/reachable_cities.py
FlightHopper/utils.py
FlightHopper.egg-info/PKG-INFO
FlightHopper.egg-info/SOURCES.txt
FlightHopper.egg-info/dependency_links.txt
FlightHopper.egg-info/requires.txt
FlightHopper.egg-info/top_level.txt