Metadata-Version: 2.1
Name: FlightHopper
Version: 1.0.2
Summary: Search for cheaper transfer fights, where your destination is the transfer city.
Home-page: https://github.com/jtc1246/FlightHopper
Author: Tiancheng Jiao
Author-email: jtc1246@outlook.com
License: GPL-2.0 License
Platform: all
Requires-Python: >=3.9
License-File: LICENSE
